radicale_remind.py
radicale_remind-0.7.1.dist-info/licenses/LICENSE
radicale_remind-0.7.1.dist-info/METADATA
radicale_remind-0.7.1.dist-info/WHEEL
radicale_remind-0.7.1.dist-info/top_level.txt
radicale_remind-0.7.1.dist-info/RECORD
