Metadata-Version: 2.4
Name: radicale-remind
Version: 0.7.1
Summary: Radicale Remind, Abook and Taskwarrior storage backend
Home-page: https://github.com/jspricke/radicale-remind
Author: Jochen Sprickerhof
Author-email: radicale@jochen.sprickerhof.de
License: GPLv3+
Keywords: Radicale
Classifier: Programming Language :: Python
Classifier: Development Status :: 4 - Beta
Classifier: Environment :: Console
Classifier: Environment :: Web Environment
Classifier: Intended Audience :: End Users/Desktop
Classifier: Intended Audience :: Information Technology
Classifier: License :: OSI Approved :: GNU General Public License v3 or later (GPLv3+)
Classifier: Operating System :: OS Independent
Classifier: Topic :: Office/Business :: Groupware
License-File: LICENSE
Requires-Dist: Radicale
Requires-Dist: abook
Requires-Dist: icstask
Requires-Dist: remind
Dynamic: author
Dynamic: author-email
Dynamic: classifier
Dynamic: description
Dynamic: home-page
Dynamic: keywords
Dynamic: license
Dynamic: license-file
Dynamic: requires-dist
Dynamic: summary
